<?xml version='1.0' encoding='UTF-8'?><factura version='1.1.0' id='comprobante'><infoTributaria><ambiente>2</ambiente><tipoEmision>1</tipoEmision><razonSocial> ANGY BIBIANA ESBERTT HERNANDEZ</razonSocial><nombreComercial> VIES IMCOM</nombreComercial><ruc>1758282840001</ruc><claveAcceso>1306202301175828284000120011000000000221234567815</claveAcceso><codDoc>01</codDoc><estab>001</estab><ptoEmi>100</ptoEmi><secuencial>000000022</secuencial><dirMatriz>SALINAS 1426 Y CHECA</dirMatriz></infoTributaria><infoFactura><fechaEmision>13/06/2023</fechaEmision><dirEstablecimiento>SALINAS 1426 Y CHECA</dirEstablecimiento><obligadoContabilidad>NO</obligadoContabilidad><tipoIdentificacionComprador>04</tipoIdentificacionComprador><razonSocialComprador>COLCHA GUAMAN BLANCA YADIRA</razonSocialComprador><identificacionComprador>1713140059001</identificacionComprador><totalSinImpuestos>325.01</totalSinImpuestos><totalDescuento>139.29</totalDescuento><totalConImpuestos><totalImpuesto><codigo>2</codigo><codigoPorcentaje>2</codigoPorcentaje><baseImponible>325.01</baseImponible><valor>39</valor></totalImpuesto></totalConImpuestos><propina>0.00</propina><importeTotal>364.01</importeTotal><moneda>DOLAR</moneda><pagos><pago><formaPago>20</formaPago><total>364.01</total></pago></pagos></infoFactura><detalles><detalle><codigoPrincipal>UR.GUA.001</codigoPrincipal><descripcion>CARTON DE GUANTE UR NEGRO TALLA M</descripcion><cantidad>2</cantidad><precioUnitario>46.43</precioUnitario><descuento>0</descuento><precioTotalSinImpuesto>92.86</precioTotalSinImpuesto><impuestos><impuesto><codigo>2</codigo><codigoPorcentaje>2</codigoPorcentaje><tarifa>12</tarifa><baseImponible>92.86</baseImponible><valor>11.14</valor></impuesto></impuestos></detalle><detalle><codigoPrincipal>UR.GUA.002</codigoPrincipal><descripcion>CARTON DE GUANTE UR NEGRO TALLA L</descripcion><cantidad>2</cantidad><precioUnitario>46.43</precioUnitario><descuento>0</descuento><precioTotalSinImpuesto>92.86</precioTotalSinImpuesto><impuestos><impuesto><codigo>2</codigo><codigoPorcentaje>2</codigoPorcentaje><tarifa>12</tarifa><baseImponible>92.86</baseImponible><valor>11.14</valor></impuesto></impuestos></detalle><detalle><codigoPrincipal>UR.GUA.004</codigoPrincipal><descripcion>CARTON DE GUANTE UR AZUL TALLA M</descripcion><cantidad>2</cantidad><precioUnitario>46.43</precioUnitario><descuento>0</descuento><precioTotalSinImpuesto>92.86</precioTotalSinImpuesto><impuestos><impuesto><codigo>2</codigo><codigoPorcentaje>2</codigoPorcentaje><tarifa>12</tarifa><baseImponible>92.86</baseImponible><valor>11.14</valor></impuesto></impuestos></detalle><detalle><codigoPrincipal>UR.GUA.005</codigoPrincipal><descripcion>CARTON DE GUANTE UR AZUL TALLA L</descripcion><cantidad>1</cantidad><precioUnitario>46.43</precioUnitario><descuento>0</descuento><precioTotalSinImpuesto>46.43</precioTotalSinImpuesto><impuestos><impuesto><codigo>2</codigo><codigoPorcentaje>2</codigoPorcentaje><tarifa>12</tarifa><baseImponible>46.43</baseImponible><valor>5.57</valor></impuesto></impuestos></detalle><detalle><codigoPrincipal>UR.GUA.003</codigoPrincipal><descripcion>CARTON DE GUANTE UR AZUL TALLA S</descripcion><cantidad>1</cantidad><precioUnitario>46.43</precioUnitario><descuento>46.43</descuento><precioTotalSinImpuesto>0</precioTotalSinImpuesto><impuestos><impuesto><codigo>2</codigo><codigoPorcentaje>2</codigoPorcentaje><tarifa>12</tarifa><baseImponible>0</baseImponible><valor>0</valor></impuesto></impuestos></detalle><detalle><codigoPrincipal>UR.GUA.006</codigoPrincipal><descripcion>CARTON DE GUANTE UR AZUL TALLA L P</descripcion><cantidad>1</cantidad><precioUnitario>46.43</precioUnitario><descuento>46.43</descuento><precioTotalSinImpuesto>0</precioTotalSinImpuesto><impuestos><impuesto><codigo>2</codigo><codigoPorcentaje>2</codigoPorcentaje><tarifa>12</tarifa><baseImponible>0</baseImponible><valor>0</valor></impuesto></impuestos></detalle><detalle><codigoPrincipal>UR.GUA.007</codigoPrincipal><descripcion>CARTON DE GUANTE UR NEGRO TALLA L P</descripcion><cantidad>1</cantidad><precioUnitario>46.43</precioUnitario><descuento>46.43</descuento><precioTotalSinImpuesto>0</precioTotalSinImpuesto><impuestos><impuesto><codigo>2</codigo><codigoPorcentaje>2</codigoPorcentaje><tarifa>12</tarifa><baseImponible>0</baseImponible><valor>0</valor></impuesto></impuestos></detalle></detalles><infoAdicional><campoAdicional nombre='Direccion'>BENALCAZAR N6-09 Y MEJIA</campoAdicional><campoAdicional nombre='Telefono'>0994928826</campoAdicional><campoAdicional nombre='Email'>fantasiasrimar@hotmail.com</campoAdicional><campoAdicional nombre='Observaciones'> CONTRIBUYENTE REGIMEN RIMPE                   ESTA FACTURA CORRESPONDE A LA NOTA DE ENTREGA  NO. 92 DEL 03-05-2023</campoAdicional></infoAdicional></factura>